[
  {
    "titlu": "Iordania – Once in a Lifetime",
    "pret": "de la 903 €",
    "imagine": "https://www.christiantour.ro/image/cms/circuite/iordania.jpg",
    "link": "https://www.christiantour.ro/circuit/iordania-once-in-a-lifetime",
    "sursa": "Christian Tour"
  },
  {
    "titlu": "Antalya – All Inclusive",
    "pret": "de la 599 €",
    "imagine": "https://cdn.teztour.ro/images/antalya-hotel.jpg",
    "link": "https://www.teztour.ro/ro/antalya-oferte.html",
    "sursa": "Tez Tour"
  }
]
